netgen/libngsolve.dll
netgen/ngscxx.bat
netgen/ngsld.bat
netgen/include/analytic_integrals.hpp
netgen/include/arnoldi.hpp
netgen/include/bandmatrix.hpp
netgen/include/basematrix.hpp
netgen/include/basevector.hpp
netgen/include/bdbequations.hpp
netgen/include/bdbintegrator.hpp
netgen/include/bessel.hpp
netgen/include/bilinearform.hpp
netgen/include/bla.hpp
netgen/include/blockalloc.hpp
netgen/include/blockjacobi.hpp
netgen/include/bspline.hpp
netgen/include/calcinverse.hpp
netgen/include/cg.hpp
netgen/include/chebyshev.hpp
netgen/include/cholesky.hpp
netgen/include/clapack.h
netgen/include/code_generation.hpp
netgen/include/coefficient.hpp
netgen/include/coefficient_impl.hpp
netgen/include/coefficient_stdmath.hpp
netgen/include/commutingAMG.hpp
netgen/include/comp.hpp
netgen/include/compatibility.hpp
netgen/include/complex_wrapper.hpp
netgen/include/compressedfespace.hpp
netgen/include/contact.hpp
netgen/include/diagonalmatrix.hpp
netgen/include/differentialoperator.hpp
netgen/include/diffop.hpp
netgen/include/diffop_impl.hpp
netgen/include/discontinuous.hpp
netgen/include/dump.hpp
netgen/include/ectypes.hpp
netgen/include/eigen.hpp
netgen/include/eigensystem.hpp
netgen/include/elasticity_equations.hpp
netgen/include/elementbyelement.hpp
netgen/include/elementtopology.hpp
netgen/include/elementtransformation.hpp
netgen/include/evalfunc.hpp
netgen/include/expr.hpp
netgen/include/facetfe.hpp
netgen/include/facetfespace.hpp
netgen/include/facethofe.hpp
netgen/include/facetsurffespace.hpp
netgen/include/fe_interfaces.hpp
netgen/include/fem.hpp
netgen/include/fesconvert.hpp
netgen/include/fespace.hpp
netgen/include/finiteelement.hpp
netgen/include/globalinterfacespace.hpp
netgen/include/globalspace.hpp
netgen/include/gridfunction.hpp
netgen/include/h1amg.hpp
netgen/include/h1hofe.hpp
netgen/include/h1hofe_impl.hpp
netgen/include/h1hofefo.hpp
netgen/include/h1hofefo_impl.hpp
netgen/include/h1hofespace.hpp
netgen/include/h1lofe.hpp
netgen/include/h1lumping.hpp
ngsolve-6.2.2506.dist-info/licenses/LICENSE
ngsolve-6.2.2506.dist-info/METADATA
ngsolve-6.2.2506.dist-info/WHEEL
ngsolve-6.2.2506.dist-info/top_level.txt
ngsolve-6.2.2506.dist-info/RECORD
