Metadata-Version: 2.4
Name: ngsolve
Version: 6.2.2506
Summary: NGSolve
Author: The NGSolve team
License: LGPL2.1
License-File: LICENSE
Requires-Dist: netgen-mesher==6.2.2506
Requires-Dist: mkl
Dynamic: author
Dynamic: license
Dynamic: license-file
Dynamic: requires-dist
Dynamic: summary
